torch_batteries/__init__.py
torch_batteries/const.py
torch_batteries/py.typed
torch_batteries/callbacks/__init__.py
torch_batteries/callbacks/early_stopping.py
torch_batteries/callbacks/experiment_tracking.py
torch_batteries/callbacks/model_checkpoint.py
torch_batteries/events/__init__.py
torch_batteries/events/core.py
torch_batteries/events/handler.py
torch_batteries/tracking/__init__.py
torch_batteries/tracking/base.py
torch_batteries/tracking/types.py
torch_batteries/tracking/wandb.py
torch_batteries/trainer/__init__.py
torch_batteries/trainer/core.py
torch_batteries/trainer/types.py
torch_batteries/utils/__init__.py
torch_batteries/utils/batch.py
torch_batteries/utils/device.py
torch_batteries/utils/formatting.py
torch_batteries/utils/logging.py
torch_batteries/utils/metrics.py
torch_batteries/utils/progress/__init__.py
torch_batteries/utils/progress/base.py
torch_batteries/utils/progress/factory.py
torch_batteries/utils/progress/progress_bar.py
torch_batteries/utils/progress/silent.py
torch_batteries/utils/progress/simple.py
torch_batteries/utils/progress/types.py
torch_batteries-0.5.2.dist-info/licenses/LICENSE
torch_batteries-0.5.2.dist-info/METADATA
torch_batteries-0.5.2.dist-info/WHEEL
torch_batteries-0.5.2.dist-info/top_level.txt
torch_batteries-0.5.2.dist-info/RECORD
