Metadata-Version: 2.4
Name: torch-batteries
Version: 0.5.2
Summary: A lightweight Python package that supplies batteries-included abstractions for PyTorch workflows
Author: Michal Szczygiel, Arkadiusz Paterak, Antoni Zięciak
License-Expression: MIT
Project-URL: Homepage, https://github.com/michalszc/torch-batteries
Project-URL: Repository, https://github.com/michalszc/torch-batteries
Project-URL: Issues, https://github.com/michalszc/torch-batteries/issues
Keywords: pytorch,machine learning,deep learning,training,evaluation
Classifier: Development Status :: 1 - Planning
Classifier: Intended Audience :: Developers
Classifier: Intended Audience :: Science/Research
Classifier: Programming Language :: Python :: 3
Classifier: Programming Language :: Python :: 3.12
Classifier: Topic :: Scientific/Engineering :: Artificial Intelligence
Classifier: Topic :: Software Development :: Libraries :: Python Modules
Requires-Python: >=3.12
License-File: LICENSE
Requires-Dist: torch>=2.9.0
Requires-Dist: tqdm>=4.67.1
Provides-Extra: example
Requires-Dist: ipykernel>=7.1.0; extra == "example"
Requires-Dist: matplotlib>=3.10.7; extra == "example"
Requires-Dist: numpy>=2.3.4; extra == "example"
Requires-Dist: scikit-learn>=1.7.2; extra == "example"
Requires-Dist: seaborn>=0.13.2; extra == "example"
Requires-Dist: torchvision>=0.24.1; extra == "example"
Provides-Extra: wandb
Requires-Dist: wandb>=0.16.0; extra == "wandb"
Requires-Dist: nbformat>=5.10.4; extra == "wandb"
Dynamic: license-file
